video_cut/__init__.py
video_cut/align_audio_video.py
video_cut/concat_videos.py
video_cut/cut_timeframes.py
video_cut/cut_video.py
video_cut/support.py
video_cut-0.0.11.dist-info/METADATA
video_cut-0.0.11.dist-info/WHEEL
video_cut-0.0.11.dist-info/top_level.txt
video_cut-0.0.11.dist-info/RECORD
