Metadata-Version: 2.1
Name: video-cut
Version: 0.0.11
Summary: Youtube video uploader
Home-page: https://github.com/remorses/video_cut
Author: Tommaso De Rossi
Author-email: beats.by.morse@gmail.com
License: MIT
Platform: UNKNOWN
